<?xml version="1.0" encoding="UTF-8" ?>
<Grafo ponderado="false" dirigido="false">
	<Vertices>
		<!-- relId indica o índice do vértice na matriz de adjacências-->
		<Vertice relId="0" rotulo="A" posX="198" posY="114"/>
		<Vertice relId="1" rotulo="B" posX="383" posY="63"/>
		<Vertice relId="2" rotulo="C" posX="449" posY="117"/>
		<Vertice relId="3" rotulo="D" posX="250" posY="53"/>
		<Vertice relId="4" rotulo="E" posX="434" posY="236"/>
		<Vertice relId="5" rotulo="F" posX="299" posY="233"/>
		<Vertice relId="6" rotulo="G" posX="339" posY="176"/>
		<Vertice relId="7" rotulo="H" posX="219" posY="216"/>
		<Vertice relId="8" rotulo="I" posX="229" posY="289"/>
		<Vertice relId="9" rotulo="J" posX="275" posY="378"/>
		<Vertice relId="10" rotulo="K" posX="332" posY="305"/>
		<Vertice relId="11" rotulo="L" posX="424" posY="354"/>
	</Vertices>
	<Arestas>
		<Aresta idVertice1="0" idVertice2="1" peso="1.0"/>
		<Aresta idVertice1="0" idVertice2="3" peso="1.0"/>
		<Aresta idVertice1="1" idVertice2="2" peso="1.0"/>
		<Aresta idVertice1="1" idVertice2="7" peso="1.0"/>
		<Aresta idVertice1="2" idVertice2="0" peso="1.0"/>
		<Aresta idVertice1="3" idVertice2="2" peso="1.0"/>
		<Aresta idVertice1="3" idVertice2="6" peso="1.0"/>
		<Aresta idVertice1="3" idVertice2="1" peso="1.0"/>
		<Aresta idVertice1="3" idVertice2="5" peso="1.0"/>
		<Aresta idVertice1="3" idVertice2="7" peso="1.0"/>
		<Aresta idVertice1="4" idVertice2="2" peso="1.0"/>
		<Aresta idVertice1="4" idVertice2="10" peso="1.0"/>
		<Aresta idVertice1="4" idVertice2="1" peso="1.0"/>
		<Aresta idVertice1="4" idVertice2="7" peso="1.0"/>
		<Aresta idVertice1="4" idVertice2="3" peso="1.0"/>
		<Aresta idVertice1="5" idVertice2="6" peso="1.0"/>
		<Aresta idVertice1="5" idVertice2="0" peso="1.0"/>
		<Aresta idVertice1="5" idVertice2="4" peso="1.0"/>
		<Aresta idVertice1="5" idVertice2="1" peso="1.0"/>
		<Aresta idVertice1="5" idVertice2="2" peso="1.0"/>
		<Aresta idVertice1="5" idVertice2="9" peso="1.0"/>
		<Aresta idVertice1="6" idVertice2="0" peso="1.0"/>
		<Aresta idVertice1="6" idVertice2="1" peso="1.0"/>
		<Aresta idVertice1="6" idVertice2="2" peso="1.0"/>
		<Aresta idVertice1="6" idVertice2="4" peso="1.0"/>
		<Aresta idVertice1="6" idVertice2="11" peso="1.0"/>
		<Aresta idVertice1="6" idVertice2="10" peso="1.0"/>
		<Aresta idVertice1="7" idVertice2="6" peso="1.0"/>
		<Aresta idVertice1="7" idVertice2="0" peso="1.0"/>
		<Aresta idVertice1="7" idVertice2="5" peso="1.0"/>
		<Aresta idVertice1="8" idVertice2="5" peso="1.0"/>
		<Aresta idVertice1="8" idVertice2="7" peso="1.0"/>
		<Aresta idVertice1="8" idVertice2="6" peso="1.0"/>
		<Aresta idVertice1="8" idVertice2="9" peso="1.0"/>
		<Aresta idVertice1="8" idVertice2="10" peso="1.0"/>
		<Aresta idVertice1="8" idVertice2="11" peso="1.0"/>
		<Aresta idVertice1="9" idVertice2="10" peso="1.0"/>
		<Aresta idVertice1="10" idVertice2="5" peso="1.0"/>
		<Aresta idVertice1="10" idVertice2="11" peso="1.0"/>
		<Aresta idVertice1="10" idVertice2="2" peso="1.0"/>
		<Aresta idVertice1="10" idVertice2="7" peso="1.0"/>
		<Aresta idVertice1="11" idVertice2="9" peso="1.0"/>
		<Aresta idVertice1="11" idVertice2="4" peso="1.0"/>
	</Arestas>
</Grafo>